ks_market_api/__init__.py
ks_market_api/api.py
ks_market_api/config.py
ks_market_engine-1.1.12.dist-info/METADATA
ks_market_engine-1.1.12.dist-info/WHEEL
ks_market_engine-1.1.12.dist-info/RECORD
