Metadata-Version: 2.4
Name: ks_market_engine
Version: 1.1.12
License-Expression: MIT
Requires-Python: >=3.8
Requires-Dist: ks-futu-market-api>=1.0.1
Requires-Dist: ks-trade-api>=0.0.65
Requires-Dist: ks-utility>=0.0.32
